PyOpenColorIO-stubs/__init__.pyi
PyOpenColorIO-stubs/py.typed
types_opencolorio-2.2.1.2.dist-info/METADATA
types_opencolorio-2.2.1.2.dist-info/WHEEL
types_opencolorio-2.2.1.2.dist-info/RECORD
